CHANGES.txt
LICENSE-legendre-gauss-lobatto-algorithm.txt
LICENSE-mpspack.txt
LICENSE.txt
MANIFEST.in
README.txt
THANKS.txt
setup.cfg
setup.py
empirical/__init__.py
empirical/basis.py
empirical/domain.py
empirical/eim.py
empirical/emfs.py
empirical/interpolate.py
empirical/mesh.py
empirical/problem.py
empirical/quadrature.py
empirical/utils.py
empirical.egg-info/PKG-INFO
empirical.egg-info/SOURCES.txt
empirical.egg-info/dependency_links.txt
empirical.egg-info/requires.txt
empirical.egg-info/top_level.txt
examples/emfs_helmholtz.py
examples/mfs_analytic_continuation.py
examples/mfs_convergence.py
examples/tut_scatt.py
examples/eim/example1.py
examples/eim/example1_2d.py
examples/eim/example2.py
examples/eim/example2_2d.py
examples/eim/example3.py
tests/test_bvp.py
tests/test_domain.py
tests/test_interpolate.py
tests/test_mesh.py
tests/test_mfsbasis.py
tests/test_quadrature.py
tests/test_scattering.py
tests/test_segment.py